setup.py
./function_scheduling_distributed_framework/__init__.py
./function_scheduling_distributed_framework/frame_config.py
./function_scheduling_distributed_framework/nb_log_config.py
./function_scheduling_distributed_framework/set_frame_config.py
./function_scheduling_distributed_framework/concurrent_pool/__init__.py
./function_scheduling_distributed_framework/concurrent_pool/async_helper.py
./function_scheduling_distributed_framework/concurrent_pool/async_pool_executor.py
./function_scheduling_distributed_framework/concurrent_pool/bounded_threadpoolexcutor.py
./function_scheduling_distributed_framework/concurrent_pool/custom_evenlet_pool_executor.py
./function_scheduling_distributed_framework/concurrent_pool/custom_gevent_pool_executor.py
./function_scheduling_distributed_framework/concurrent_pool/custom_threadpool_executor.py
./function_scheduling_distributed_framework/concurrent_pool/custom_threadpool_executor0.py
./function_scheduling_distributed_framework/consumers/__init__.py
./function_scheduling_distributed_framework/consumers/base_consumer.py
./function_scheduling_distributed_framework/consumers/confirm_mixin.py
./function_scheduling_distributed_framework/consumers/kafka_consumer.py
./function_scheduling_distributed_framework/consumers/local_python_queue_consumer.py
./function_scheduling_distributed_framework/consumers/mongomq_consumer.py
./function_scheduling_distributed_framework/consumers/nsq_consumer.py
./function_scheduling_distributed_framework/consumers/persist_queue_consumer.py
./function_scheduling_distributed_framework/consumers/rabbitmq_amqpstorm_consumer.py
./function_scheduling_distributed_framework/consumers/rabbitmq_pika_consumer.py
./function_scheduling_distributed_framework/consumers/rabbitmq_rabbitpy_consumer.py
./function_scheduling_distributed_framework/consumers/redis_consumer.py
./function_scheduling_distributed_framework/consumers/redis_consumer_ack_able.py
./function_scheduling_distributed_framework/consumers/redis_filter.py
hmdc.egg-info/PKG-INFO
hmdc.egg-info/SOURCES.txt
hmdc.egg-info/dependency_links.txt
hmdc.egg-info/requires.txt
hmdc.egg-info/top_level.txt