Metadata-Version: 2.1
Name: hmdc
Version: 1.0
Summary: Distributed filesystem for Hamuna AI
Home-page: https://www.hamuna.club
Author: O.Push
Author-email: opush.developer@outlook.com
License: MIT
Platform: all
